{"result":1,"shareblog":[{"id":1,"b_id":1,"uPhone":"15300018933","uNickname":"晴明","uImg":"qingming.jpg","bike":{"id":1,"img":"shandi.jpg","timeValue":"1天","request":"不要弄坏","bikekind":1,"bikename":"旅行车","userId":1},"date":"04月01日 17:10"},{"id":2,"b_id":2,"uPhone":"15300018933","uNickname":"晴明","uImg":"qingming.jpg","bike":{"id":2,"img":"lvxing.jpg","timeValue":"2天","request":"洗车","bikekind":2,"bikename":"山地车","userId":1},"date":"04月02日 17:10"},{"id":3,"b_id":3,"uPhone":"15300018922","uNickname":"神乐","uImg":"shenyue.jpg","bike":{"id":3,"img":"shandi.jpg","timeValue":"1天","request":"不要弄坏","bikekind":1,"bikename":"旅行车","userId":2},"date":"04月03日 17:11"}]}